LICENSE
MANIFEST.in
bootstrap.py
buildout.cfg
setup.cfg
setup.py
examples/ikazuchi.conf
examples/issue5.rst
examples/sample_format.rst
src/README.txt
src/TODO.txt
src/ikazuchi/__init__.py
src/ikazuchi/conf.py
src/ikazuchi/errors.py
src/ikazuchi/ikazuchi.py
src/ikazuchi/utils.py
src/ikazuchi.egg-info/PKG-INFO
src/ikazuchi.egg-info/SOURCES.txt
src/ikazuchi.egg-info/dependency_links.txt
src/ikazuchi.egg-info/entry_points.txt
src/ikazuchi.egg-info/namespace_packages.txt
src/ikazuchi.egg-info/requires.txt
src/ikazuchi.egg-info/top_level.txt
src/ikazuchi/core/__init__.py
src/ikazuchi/core/handler/__init__.py
src/ikazuchi/core/handler/base.py
src/ikazuchi/core/handler/text.py
src/ikazuchi/core/handler/utils.py
src/ikazuchi/core/translator/__init__.py
src/ikazuchi/core/translator/google.py
src/ikazuchi/core/translator/microsoft.py
src/ikazuchi/core/translator/utils.py
src/ikazuchi/locale/__init__.py
src/ikazuchi/plugins/__init__.py
src/ikazuchi/plugins/rstfile.py
src/ikazuchi/plugins/utils.py
src/ikazuchi/tests/test_conf.py
src/ikazuchi/tests/test_enrai.py
src/ikazuchi/tests/test_google_translator.py
src/ikazuchi/tests/test_handler.py
src/ikazuchi/tests/test_microsoft_translator.py
src/ikazuchi/tests/test_pep8.py
src/ikazuchi/tests/test_raimei.py
src/ikazuchi/tests/test_rstfile_handler.py
src/ikazuchi/tests/test_translator.py
src/ikazuchi/tests/test_utils.py
src/ikazuchi/tests/data/__init__.py
src/ikazuchi/tests/data/rst/__init__.py
src/ikazuchi/tests/data/rst/api_call_directive.py
src/ikazuchi/tests/data/rst/api_call_get_table_column_width.py
src/ikazuchi/tests/data/rst/api_call_lineblock.py
src/ikazuchi/tests/data/rst/api_call_listblock.py
src/ikazuchi/tests/data/rst/api_call_markup_notranslate.py
src/ikazuchi/tests/data/rst/api_call_paragraph.py
src/ikazuchi/tests/data/rst/api_call_section.py
src/ikazuchi/tests/data/rst/api_call_sourceblock.py
src/ikazuchi/tests/data/rst/api_call_split_text.py
src/ikazuchi/tests/data/rst/api_call_split_text_ja.py
src/ikazuchi/tests/data/rst/api_call_tableblock.py
src/ikazuchi/tests/data/rst/api_call_text_with_indent.py
src/ikazuchi/tests/data/rst/parse_directive.py
src/ikazuchi/tests/data/rst/parse_lineblock.py
src/ikazuchi/tests/data/rst/parse_listblock.py
