Metadata-Version: 1.1
Name: ikazuchi
Version: 0.5.6
Summary: ikazuchi helps to translate document using web translate APIs efficiently
Home-page: http://t2y.bitbucket.org/ikazuchi/build/html/index.html
Author: Tetsuya Morimoto
Author-email: tetsuya.morimoto@gmail.com
License: Apache License 2.0
Keywords: translate,i18n,internationalization
Platform: UNKNOWN
Classifier: Development Status :: 4 - Beta
Classifier: Environment :: Console
Classifier: Environment :: Web Environment
Classifier: Intended Audience :: Developers
Classifier: Intended Audience :: System Administrators
Classifier: License :: OSI Approved :: Apache Software License
Classifier: Operating System :: MacOS :: MacOS X
Classifier: Operating System :: Microsoft :: Windows
Classifier: Operating System :: POSIX
Classifier: Programming Language :: Python :: 2.6
Classifier: Programming Language :: Python :: 2.7
Classifier: Programming Language :: Python :: 2 :: Only
Classifier: Topic :: Software Development
Classifier: Topic :: Software Development :: Internationalization
